scraper_playwright.py
scraper_requests.py
github_copilot_chat_exporter-1.1.0.dist-info/licenses/LICENSE
github_copilot_chat_exporter-1.1.0.dist-info/METADATA
github_copilot_chat_exporter-1.1.0.dist-info/WHEEL
github_copilot_chat_exporter-1.1.0.dist-info/entry_points.txt
github_copilot_chat_exporter-1.1.0.dist-info/top_level.txt
github_copilot_chat_exporter-1.1.0.dist-info/RECORD
