Metadata-Version: 2.4
Name: github-copilot-chat-exporter
Version: 1.1.0
Summary: Export GitHub Copilot shared conversations to Markdown with file attachment capture
Home-page: https://github.com/pandaxbacon/github-copilot-chat-exporter
Author: Terry Pang
Classifier: Development Status :: 5 - Production/Stable
Classifier: Intended Audience :: Developers
Classifier: License :: OSI Approved :: MIT License
Classifier: Programming Language :: Python :: 3
Classifier: Programming Language :: Python :: 3.9
Classifier: Programming Language :: Python :: 3.10
Classifier: Programming Language :: Python :: 3.11
Classifier: Programming Language :: Python :: 3.12
Classifier: Programming Language :: Python :: 3.13
Requires-Python: >=3.9
License-File: LICENSE
Requires-Dist: beautifulsoup4==4.12.3
Requires-Dist: playwright==1.48.0
Requires-Dist: requests==2.32.3
Dynamic: author
Dynamic: classifier
Dynamic: description
Dynamic: description-content-type
Dynamic: home-page
Dynamic: license-file
Dynamic: requires-dist
Dynamic: requires-python
Dynamic: summary
